{
    "data": [
        {
            "ui_id": 1844,
            "title": "KHÓA KÍCH HOẠT",
            "url": "/khoa-kich-hoat",
            "status": true,
            "params": [],
            "type": "ui",
            "create_at": "2023-10-10T08:54:45.359Z",
            "create_by": {
                "username": "administrator",
                "fullname": "Administrator"
            },
            "components": [
                {
                    "component_id": 1845,
                    "component_name": "KHÓA KÍCH HOẠT",
                    "layout_id": 0,
                    "api_get": "/api/6D5FCDEAA36F49D89CA933A190C6DD23",
                    "api_post": "/ui/6305EAE210C74305A1CF1E8427B63BCE",
                    "api_put": "/ui/5FF0B0F5A2964E49A36C5047FE3287A7",
                    "api_delete": "/ui/0E28BB60F90444F49B914F67C272769C",
                    "api_search": "/search/23D020124A134FC5B4924BED76AFCA82",
                    "api_export": "/export/B25B5BFD66FF44FA8BBE91355ECAB5D0",
                    "api_import": "/import/6F4E09E395FB41C3AAD07AF67E6CC158",
                    "api_detail": "/d/940A626C00DC4CE690907B1FB1D2CE83"
                }
            ]
        },
        {
            "ui_id": 1874,
            "title": "KEYS",
            "url": "/keys",
            "status": true,
            "params": [
                1730
            ],
            "type": "ui",
            "create_at": "2023-10-11T02:59:20.627Z",
            "create_by": {
                "username": "administrator",
                "fullname": "Administrator"
            },
            "components": [
                {
                    "component_id": 1875,
                    "component_name": "KEYS",
                    "layout_id": 0,
                    "api_get": "/api/A44ED43CE42B4C7CAE8403D6B62ACF8E",
                    "api_post": "/ui/AA9B4591FE5F4A5789582207C5064C1F",
                    "api_put": "/ui/60D70E4526514205909FA59ABC4CD728",
                    "api_delete": "/ui/FE97593DF345400BA08D57AA5E32E42C",
                    "api_search": "/search/ABF84B95C6B4440EB0E021B8FF6ED3FF",
                    "api_export": "/export/26A9B832B276492DADBC4282B2E80EA4",
                    "api_import": "/import/8C000C9E57E94383BC0FA47FF731EB4F",
                    "api_detail": "/d/03710DEE03DB4BB5B0A531248A1614C8"
                }
            ]
        }
    ]
}